{
  "schema_version": 1,
  "city": "pleszew",
  "plots": [
    {
      "key": "dz|nowej wsi|249/7",
      "kind": "grunt",
      "city": "pleszew",
      "dzialka_nr": "249/7",
      "obreb": "Nowej Wsi",
      "street": null,
      "building": null,
      "address_raw": "Nowej Wsi",
      "dzialka_id": null,
      "geoportal_url": "https://www.google.com/search?q=dzia%C5%82ka%20249%2F7%20Nowej%20Wsi%20Nowej%20Wsi%20Pleszew%20geoportal%20dzia%C5%82ki",
      "area_m2": 869,
      "zoning": null,
      "status": null,
      "listings": [
        {
          "date": "2025-07-08",
          "round": 1,
          "starting_price_pln": 91020,
          "outcome": "unsold",
          "area_m2": 869
        },
        {
          "date": "2025-09-15",
          "round": 2,
          "starting_price_pln": 91020,
          "outcome": "unsold",
          "area_m2": 869
        },
        {
          "date": "2026-08-18",
          "round": 4,
          "starting_price_pln": 91020,
          "outcome": "active",
          "area_m2": 869,
          "detail_url": "https://bip.pleszew.pl/pleszewm/zasoby/files/nieruchomosci/2026/gp-obw-10072026.pdf"
        }
      ],
      "parcels": [
        {
          "nr": "249/7"
        }
      ]
    },
    {
      "key": "dz|nowej wsi|249/8",
      "kind": "grunt",
      "city": "pleszew",
      "dzialka_nr": "249/8",
      "obreb": "Nowej Wsi",
      "street": null,
      "building": null,
      "address_raw": "Nowej Wsi",
      "dzialka_id": null,
      "geoportal_url": "https://www.google.com/search?q=dzia%C5%82ka%20249%2F8%20Nowej%20Wsi%20Nowej%20Wsi%20Pleszew%20geoportal%20dzia%C5%82ki",
      "area_m2": 860,
      "zoning": null,
      "status": null,
      "listings": [
        {
          "date": "2025-07-08",
          "round": 1,
          "starting_price_pln": 91020,
          "outcome": "unsold",
          "area_m2": 860
        },
        {
          "date": "2025-09-15",
          "round": 2,
          "starting_price_pln": 91020,
          "outcome": "unsold",
          "area_m2": 860
        },
        {
          "date": "2026-08-18",
          "round": 4,
          "starting_price_pln": 91020,
          "outcome": "active",
          "area_m2": 860,
          "detail_url": "https://bip.pleszew.pl/pleszewm/zasoby/files/nieruchomosci/2026/gp-obw-10072026.pdf"
        }
      ],
      "parcels": [
        {
          "nr": "249/8"
        }
      ]
    },
    {
      "key": "dz|nowej wsi|249/9",
      "kind": "grunt",
      "city": "pleszew",
      "dzialka_nr": "249/9",
      "obreb": "Nowej Wsi",
      "street": null,
      "building": null,
      "address_raw": "Nowej Wsi",
      "dzialka_id": null,
      "geoportal_url": "https://www.google.com/search?q=dzia%C5%82ka%20249%2F9%20Nowej%20Wsi%20Nowej%20Wsi%20Pleszew%20geoportal%20dzia%C5%82ki",
      "area_m2": 860,
      "zoning": null,
      "status": null,
      "listings": [
        {
          "date": "2025-07-08",
          "round": 1,
          "starting_price_pln": 91020,
          "outcome": "unsold",
          "area_m2": 860
        },
        {
          "date": "2025-09-15",
          "round": 2,
          "starting_price_pln": null,
          "outcome": "unsold",
          "area_m2": 860
        },
        {
          "date": "2026-08-18",
          "round": 4,
          "starting_price_pln": 91020,
          "outcome": "active",
          "area_m2": 860,
          "detail_url": "https://bip.pleszew.pl/pleszewm/zasoby/files/nieruchomosci/2026/gp-obw-10072026.pdf"
        }
      ],
      "parcels": [
        {
          "nr": "249/9"
        }
      ]
    },
    {
      "key": "dz|nowa wieś|249/7",
      "kind": "grunt",
      "city": "pleszew",
      "dzialka_nr": "249/7",
      "obreb": "Nowa Wieś",
      "street": null,
      "building": null,
      "address_raw": "Nowa Wieś",
      "dzialka_id": null,
      "geoportal_url": "https://www.google.com/search?q=dzia%C5%82ka%20249%2F7%20Nowa%20Wie%C5%9B%20Nowa%20Wie%C5%9B%20Pleszew%20geoportal%20dzia%C5%82ki",
      "area_m2": 869,
      "zoning": null,
      "status": null,
      "listings": [
        {
          "date": "2026-04-15",
          "round": 3,
          "starting_price_pln": 91020,
          "outcome": "unsold",
          "area_m2": 869
        }
      ],
      "parcels": [
        {
          "nr": "249/7"
        }
      ]
    },
    {
      "key": "dz|nowa wieś|249/8",
      "kind": "grunt",
      "city": "pleszew",
      "dzialka_nr": "249/8",
      "obreb": "Nowa Wieś",
      "street": null,
      "building": null,
      "address_raw": "Nowa Wieś",
      "dzialka_id": null,
      "geoportal_url": "https://www.google.com/search?q=dzia%C5%82ka%20249%2F8%20Nowa%20Wie%C5%9B%20Nowa%20Wie%C5%9B%20Pleszew%20geoportal%20dzia%C5%82ki",
      "area_m2": 860,
      "zoning": null,
      "status": null,
      "listings": [
        {
          "date": "2026-04-15",
          "round": 3,
          "starting_price_pln": 91020,
          "outcome": "unsold",
          "area_m2": 860
        }
      ],
      "parcels": [
        {
          "nr": "249/8"
        }
      ]
    },
    {
      "key": "dz|nowa wieś|249/9",
      "kind": "grunt",
      "city": "pleszew",
      "dzialka_nr": "249/9",
      "obreb": "Nowa Wieś",
      "street": null,
      "building": null,
      "address_raw": "Nowa Wieś",
      "dzialka_id": null,
      "geoportal_url": "https://www.google.com/search?q=dzia%C5%82ka%20249%2F9%20Nowa%20Wie%C5%9B%20Nowa%20Wie%C5%9B%20Pleszew%20geoportal%20dzia%C5%82ki",
      "area_m2": 860,
      "zoning": null,
      "status": null,
      "listings": [
        {
          "date": "2026-04-15",
          "round": 3,
          "starting_price_pln": 91020,
          "outcome": "unsold",
          "area_m2": 860
        }
      ],
      "parcels": [
        {
          "nr": "249/9"
        }
      ]
    },
    {
      "key": "dz|pleszewie|1806/26",
      "kind": "grunt",
      "city": "pleszew",
      "dzialka_nr": "1806/26",
      "obreb": "Pleszewie",
      "street": null,
      "building": null,
      "address_raw": "Pleszewie",
      "dzialka_id": null,
      "geoportal_url": "https://www.google.com/search?q=dzia%C5%82ka%201806%2F26%20Pleszewie%20Pleszewie%20Pleszew%20geoportal%20dzia%C5%82ki",
      "area_m2": 152,
      "zoning": null,
      "status": null,
      "listings": [
        {
          "date": "2026-02-10",
          "round": 1,
          "starting_price_pln": 154980,
          "outcome": "archived",
          "area_m2": 152,
          "detail_url": "https://bip.pleszew.pl/pleszewm/zasoby/files/ogloszenia/2026/gp-ogl-07012026.pdf"
        }
      ],
      "parcels": [
        {
          "nr": "1806/26"
        }
      ]
    },
    {
      "key": "dz|pleszewie|1854/1",
      "kind": "grunt",
      "city": "pleszew",
      "dzialka_nr": "1854/1",
      "obreb": "Pleszewie",
      "street": null,
      "building": null,
      "address_raw": "Pleszewie",
      "dzialka_id": null,
      "geoportal_url": "https://www.google.com/search?q=dzia%C5%82ka%201854%2F1%20Pleszewie%20Pleszewie%20Pleszew%20geoportal%20dzia%C5%82ki",
      "area_m2": 8146,
      "zoning": null,
      "status": null,
      "listings": [
        {
          "date": "2026-02-10",
          "round": 1,
          "starting_price_pln": 154980,
          "outcome": "archived",
          "area_m2": 8146,
          "detail_url": "https://bip.pleszew.pl/pleszewm/zasoby/files/ogloszenia/2026/gp-ogl-07012026.pdf"
        }
      ],
      "parcels": [
        {
          "nr": "1854/1"
        }
      ]
    },
    {
      "key": "dz|pleszewie|1854/2",
      "kind": "grunt",
      "city": "pleszew",
      "dzialka_nr": "1854/2",
      "obreb": "Pleszewie",
      "street": null,
      "building": null,
      "address_raw": "Pleszewie",
      "dzialka_id": null,
      "geoportal_url": "https://www.google.com/search?q=dzia%C5%82ka%201854%2F2%20Pleszewie%20Pleszewie%20Pleszew%20geoportal%20dzia%C5%82ki",
      "area_m2": 743,
      "zoning": null,
      "status": null,
      "listings": [
        {
          "date": "2026-02-10",
          "round": 1,
          "starting_price_pln": 154980,
          "outcome": "archived",
          "area_m2": 743,
          "detail_url": "https://bip.pleszew.pl/pleszewm/zasoby/files/ogloszenia/2026/gp-ogl-07012026.pdf"
        }
      ],
      "parcels": [
        {
          "nr": "1854/2"
        }
      ]
    },
    {
      "key": "dz|korzkwach|128/14",
      "kind": "grunt",
      "city": "pleszew",
      "dzialka_nr": "128/14",
      "obreb": "Korzkwach",
      "street": null,
      "building": null,
      "address_raw": "Korzkwach",
      "dzialka_id": null,
      "geoportal_url": "https://www.google.com/search?q=dzia%C5%82ka%20128%2F14%20Korzkwach%20Korzkwach%20Pleszew%20geoportal%20dzia%C5%82ki",
      "area_m2": 1257,
      "zoning": null,
      "status": null,
      "listings": [
        {
          "date": "2025-06-30",
          "round": 1,
          "starting_price_pln": 131419,
          "outcome": "unsold",
          "area_m2": 1257
        },
        {
          "date": "2025-08-04",
          "round": 2,
          "starting_price_pln": 100497,
          "outcome": "unsold",
          "area_m2": 1257
        }
      ],
      "parcels": [
        {
          "nr": "128/14"
        }
      ]
    },
    {
      "key": "dz|korzkwach|129/4",
      "kind": "grunt",
      "city": "pleszew",
      "dzialka_nr": "129/4",
      "obreb": "Korzkwach",
      "street": null,
      "building": null,
      "address_raw": "Korzkwach",
      "dzialka_id": null,
      "geoportal_url": "https://www.google.com/search?q=dzia%C5%82ka%20129%2F4%20Korzkwach%20Korzkwach%20Pleszew%20geoportal%20dzia%C5%82ki",
      "area_m2": 423,
      "zoning": null,
      "status": null,
      "listings": [
        {
          "date": "2025-06-30",
          "round": 1,
          "starting_price_pln": 35955,
          "outcome": "unsold",
          "area_m2": 423
        },
        {
          "date": "2025-08-04",
          "round": 2,
          "starting_price_pln": 27495,
          "outcome": "unsold",
          "area_m2": 423
        }
      ],
      "parcels": [
        {
          "nr": "129/4"
        }
      ]
    },
    {
      "key": "dz|pacanowicach|21/7",
      "kind": "grunt",
      "city": "pleszew",
      "dzialka_nr": "21/7",
      "obreb": "Pacanowicach",
      "street": null,
      "building": null,
      "address_raw": "Pacanowicach",
      "dzialka_id": null,
      "geoportal_url": "https://www.google.com/search?q=dzia%C5%82ka%2021%2F7%20Pacanowicach%20Pacanowicach%20Pleszew%20geoportal%20dzia%C5%82ki",
      "area_m2": 835,
      "zoning": null,
      "status": null,
      "listings": [
        {
          "date": "2025-07-15",
          "round": 1,
          "starting_price_pln": 71340,
          "outcome": "sold",
          "final_price_pln": 82720,
          "area_m2": 835
        }
      ],
      "parcels": [
        {
          "nr": "21/7"
        }
      ]
    },
    {
      "key": "dz|pacanowicach|21/8",
      "kind": "grunt",
      "city": "pleszew",
      "dzialka_nr": "21/8",
      "obreb": "Pacanowicach",
      "street": null,
      "building": null,
      "address_raw": "Pacanowicach",
      "dzialka_id": null,
      "geoportal_url": "https://www.google.com/search?q=dzia%C5%82ka%2021%2F8%20Pacanowicach%20Pacanowicach%20Pleszew%20geoportal%20dzia%C5%82ki",
      "area_m2": 836,
      "zoning": null,
      "status": null,
      "listings": [
        {
          "date": "2025-07-15",
          "round": 1,
          "starting_price_pln": 71340,
          "outcome": "sold",
          "final_price_pln": 82720,
          "area_m2": 836
        }
      ],
      "parcels": [
        {
          "nr": "21/8"
        }
      ]
    },
    {
      "key": "dz|pacanowicach|21/9",
      "kind": "grunt",
      "city": "pleszew",
      "dzialka_nr": "21/9",
      "obreb": "Pacanowicach",
      "street": null,
      "building": null,
      "address_raw": "Pacanowicach",
      "dzialka_id": null,
      "geoportal_url": "https://www.google.com/search?q=dzia%C5%82ka%2021%2F9%20Pacanowicach%20Pacanowicach%20Pleszew%20geoportal%20dzia%C5%82ki",
      "area_m2": 836,
      "zoning": null,
      "status": null,
      "listings": [
        {
          "date": "2025-07-15",
          "round": 1,
          "starting_price_pln": 71340,
          "outcome": "sold",
          "final_price_pln": 82720,
          "area_m2": 836
        }
      ],
      "parcels": [
        {
          "nr": "21/9"
        }
      ]
    },
    {
      "key": "dz|pacanowicach|21/10",
      "kind": "grunt",
      "city": "pleszew",
      "dzialka_nr": "21/10",
      "obreb": "Pacanowicach",
      "street": null,
      "building": null,
      "address_raw": "Pacanowicach",
      "dzialka_id": null,
      "geoportal_url": "https://www.google.com/search?q=dzia%C5%82ka%2021%2F10%20Pacanowicach%20Pacanowicach%20Pleszew%20geoportal%20dzia%C5%82ki",
      "area_m2": 839,
      "zoning": null,
      "status": null,
      "listings": [
        {
          "date": "2025-07-15",
          "round": 1,
          "starting_price_pln": 72570,
          "outcome": "sold",
          "final_price_pln": 82720,
          "area_m2": 839
        }
      ],
      "parcels": [
        {
          "nr": "21/10"
        }
      ]
    },
    {
      "key": "dz|kuczkowie|67/1",
      "kind": "grunt",
      "city": "pleszew",
      "dzialka_nr": "67/1",
      "obreb": "Kuczkowie",
      "street": null,
      "building": null,
      "address_raw": "Kuczkowie",
      "dzialka_id": null,
      "geoportal_url": "https://www.google.com/search?q=dzia%C5%82ka%2067%2F1%20Kuczkowie%20Kuczkowie%20Pleszew%20geoportal%20dzia%C5%82ki",
      "area_m2": 1103,
      "zoning": null,
      "status": null,
      "listings": [
        {
          "date": "2025-07-01",
          "round": 1,
          "starting_price_pln": 67834,
          "outcome": "archived",
          "area_m2": 1103,
          "detail_url": "https://bip.pleszew.pl/pleszewm/zasoby/files/nieruchomosci/2025/gp-ogl-20052025.pdf"
        }
      ],
      "parcels": [
        {
          "nr": "67/1"
        }
      ]
    },
    {
      "key": "dz|kuczkowie|67/4",
      "kind": "grunt",
      "city": "pleszew",
      "dzialka_nr": "67/4",
      "obreb": "Kuczkowie",
      "street": null,
      "building": null,
      "address_raw": "Kuczkowie",
      "dzialka_id": null,
      "geoportal_url": "https://www.google.com/search?q=dzia%C5%82ka%2067%2F4%20Kuczkowie%20Kuczkowie%20Pleszew%20geoportal%20dzia%C5%82ki",
      "area_m2": 1391,
      "zoning": null,
      "status": null,
      "listings": [
        {
          "date": "2025-07-01",
          "round": 1,
          "starting_price_pln": 85546,
          "outcome": "archived",
          "area_m2": 1391,
          "detail_url": "https://bip.pleszew.pl/pleszewm/zasoby/files/nieruchomosci/2025/gp-ogl-20052025.pdf"
        }
      ],
      "parcels": [
        {
          "nr": "67/4"
        }
      ]
    },
    {
      "key": "dz|kuczkowie|67/5",
      "kind": "grunt",
      "city": "pleszew",
      "dzialka_nr": "67/5",
      "obreb": "Kuczkowie",
      "street": null,
      "building": null,
      "address_raw": "Kuczkowie",
      "dzialka_id": null,
      "geoportal_url": "https://www.google.com/search?q=dzia%C5%82ka%2067%2F5%20Kuczkowie%20Kuczkowie%20Pleszew%20geoportal%20dzia%C5%82ki",
      "area_m2": 1517,
      "zoning": null,
      "status": null,
      "listings": [
        {
          "date": "2025-07-01",
          "round": 1,
          "starting_price_pln": 93295,
          "outcome": "archived",
          "area_m2": 1517,
          "detail_url": "https://bip.pleszew.pl/pleszewm/zasoby/files/nieruchomosci/2025/gp-ogl-20052025.pdf"
        }
      ],
      "parcels": [
        {
          "nr": "67/5"
        }
      ]
    },
    {
      "key": "dz|kuczkowie|67/6",
      "kind": "grunt",
      "city": "pleszew",
      "dzialka_nr": "67/6",
      "obreb": "Kuczkowie",
      "street": null,
      "building": null,
      "address_raw": "Kuczkowie",
      "dzialka_id": null,
      "geoportal_url": "https://www.google.com/search?q=dzia%C5%82ka%2067%2F6%20Kuczkowie%20Kuczkowie%20Pleszew%20geoportal%20dzia%C5%82ki",
      "area_m2": 1605,
      "zoning": null,
      "status": null,
      "listings": [
        {
          "date": "2025-07-01",
          "round": 1,
          "starting_price_pln": 98707,
          "outcome": "archived",
          "area_m2": 1605,
          "detail_url": "https://bip.pleszew.pl/pleszewm/zasoby/files/nieruchomosci/2025/gp-ogl-20052025.pdf"
        }
      ],
      "parcels": [
        {
          "nr": "67/6"
        }
      ]
    },
    {
      "key": "dz|kowalewie|8/3",
      "kind": "grunt",
      "city": "pleszew",
      "dzialka_nr": "8/3",
      "obreb": "Kowalewie",
      "street": null,
      "building": null,
      "address_raw": "Kowalewie",
      "dzialka_id": null,
      "geoportal_url": "https://www.google.com/search?q=dzia%C5%82ka%208%2F3%20Kowalewie%20Kowalewie%20Pleszew%20geoportal%20dzia%C5%82ki",
      "area_m2": 4016,
      "zoning": null,
      "status": null,
      "listings": [
        {
          "date": "2025-04-11",
          "round": 1,
          "starting_price_pln": 395174,
          "outcome": "sold",
          "final_price_pln": 400000,
          "area_m2": 4016
        }
      ],
      "parcels": [
        {
          "nr": "8/3"
        }
      ]
    },
    {
      "key": "dz|sowinie|138/39",
      "kind": "grunt",
      "city": "pleszew",
      "dzialka_nr": "138/39",
      "obreb": "Sowinie",
      "street": null,
      "building": null,
      "address_raw": "Sowinie",
      "dzialka_id": null,
      "geoportal_url": "https://www.google.com/search?q=dzia%C5%82ka%20138%2F39%20Sowinie%20Sowinie%20Pleszew%20geoportal%20dzia%C5%82ki",
      "area_m2": 1014,
      "zoning": null,
      "status": null,
      "listings": [
        {
          "date": "2025-03-04",
          "round": 2,
          "starting_price_pln": 63960,
          "outcome": "unsold",
          "area_m2": 1014
        }
      ],
      "parcels": [
        {
          "nr": "138/39"
        }
      ]
    }
  ]
}
