{
  "schema_version": 1,
  "city": "boleslawiec",
  "properties": [
    {
      "key": "warszawskiej|1|10",
      "street": "Warszawska",
      "street_norm": "warszawskiej",
      "building": "1",
      "apt": "10",
      "kind": "mieszkalny",
      "listings": [
        {
          "date": "2026-05-08",
          "round": null,
          "kind": "mieszkalny",
          "outcome": "announced",
          "wykaz_no": null,
          "area_m2": 97.1
        },
        {
          "date": "2026-06-18",
          "round": 3,
          "kind": "mieszkalny",
          "starting_price_pln": 350000,
          "outcome": "unsold",
          "unsold_reason": "brak wpłaty wadium",
          "final_price_pln": null,
          "source_pdf": "https://www.um.boleslawiec.bip-gov.pl/public/getFile?id=251418",
          "notes": [],
          "area_m2": 97.1
        },
        {
          "date": "2026-07-13",
          "round": null,
          "kind": "mieszkalny",
          "outcome": "announced",
          "wykaz_no": null,
          "area_m2": 97.1
        },
        {
          "date": "2026-08-13",
          "round": 4,
          "kind": "mieszkalny",
          "starting_price_pln": 330000,
          "outcome": "active",
          "area_m2": 97.1,
          "detail_url": "https://xn--bolesawiec-e0b.pl/index.php/mig/sp-estate/lokale-mieszkalne/6948-lokal-mieszkalny-nr-10-po%C5%82o%C5%BCony-przy-ul-warszawskiej-nr-1-powierzchnia-u%C5%BCytkowa-mieszkania-97%2C10-m2-iv-przetarg",
          "wadium_deadline": null,
          "viewing_date": null
        }
      ],
      "area_m2": 97.1
    },
    {
      "key": "ogrodowej|4|2",
      "street": "Ogrodowa",
      "street_norm": "ogrodowej",
      "building": "4",
      "apt": "2",
      "kind": "mieszkalny",
      "listings": [
        {
          "date": "2026-06-19",
          "round": null,
          "kind": "mieszkalny",
          "outcome": "announced",
          "wykaz_no": null,
          "area_m2": 84.94
        },
        {
          "date": "2026-07-28",
          "round": 6,
          "kind": "mieszkalny",
          "starting_price_pln": 323000,
          "outcome": "active",
          "area_m2": 84.94,
          "detail_url": "https://xn--bolesawiec-e0b.pl/index.php/mig/sp-estate/lokale-mieszkalne/6890-lokal-mieszkalny-nr-2%2C-po%C5%82o%C5%BCony-przy-ul-ogrodowej-nr-4-powierzchnia-u%C5%BCytkowa-mieszkania-84%2C94-m2-vi-przetarg",
          "wadium_deadline": null,
          "viewing_date": null
        }
      ],
      "area_m2": 84.94
    },
    {
      "key": "karola miarki|3|6",
      "street": "Karola Miarki",
      "street_norm": "karola miarki",
      "building": "3",
      "apt": "6",
      "kind": "unknown",
      "listings": [
        {
          "date": "2025-11-25",
          "round": null,
          "kind": "unknown",
          "outcome": "announced",
          "wykaz_no": null,
          "area_m2": 47.15
        },
        {
          "date": "2026-06-09",
          "round": null,
          "kind": "mieszkalny",
          "outcome": "announced",
          "wykaz_no": null,
          "area_m2": 47.15
        },
        {
          "date": "2026-07-16",
          "round": 2,
          "kind": "mieszkalny",
          "starting_price_pln": 161000,
          "outcome": "active",
          "area_m2": 47.15,
          "detail_url": "https://xn--bolesawiec-e0b.pl/index.php/mig/sp-estate/lokale-mieszkalne/6863-lokal-mieszkalny-nr-6%2C-po%C5%82o%C5%BCony-przy-ul-karola-miarki-nr-3-powierzchnia-u%C5%BCytkowa-mieszkania-47%2C15-m2-ii-przetarg",
          "wadium_deadline": null,
          "viewing_date": null
        }
      ],
      "area_m2": 47.15
    },
    {
      "key": "karola miarki|3|5",
      "street": "Karola Miarki",
      "street_norm": "karola miarki",
      "building": "3",
      "apt": "5",
      "kind": "unknown",
      "listings": [
        {
          "date": "2025-11-25",
          "round": null,
          "kind": "unknown",
          "outcome": "announced",
          "wykaz_no": null,
          "area_m2": 26.21
        },
        {
          "date": "2026-06-09",
          "round": null,
          "kind": "unknown",
          "outcome": "announced",
          "wykaz_no": null,
          "area_m2": 26.21
        },
        {
          "date": "2026-07-14",
          "round": 2,
          "kind": "mieszkalny",
          "starting_price_pln": 94500,
          "outcome": "archived",
          "area_m2": 26.21,
          "detail_url": "https://xn--bolesawiec-e0b.pl/index.php/mig/sp-estate/lokale-mieszkalne/6862-lokal-mieszkalny-nr-5%2C-po%C5%82o%C5%BCony-przy-ul-karola-miarki-nr-3-powierzchnia-u%C5%BCytkowa-mieszkania-26%2C21-m2-ii-przetarg",
          "wadium_deadline": null,
          "viewing_date": null
        }
      ],
      "area_m2": 26.21
    },
    {
      "key": "plac piastowski|16|",
      "street": "Plac Piastowski",
      "street_norm": "plac piastowski",
      "building": "16",
      "apt": null,
      "kind": "zabudowana",
      "listings": [
        {
          "date": "2026-04-15",
          "round": null,
          "kind": "zabudowana",
          "outcome": "announced",
          "wykaz_no": null
        },
        {
          "date": "2026-06-25",
          "round": 1,
          "kind": "zabudowana",
          "starting_price_pln": 499000,
          "outcome": "archived",
          "area_m2": null,
          "land_area_m2": 703,
          "detail_url": "https://xn--bolesawiec-e0b.pl/index.php/mig/sp-estate/lokale-budynki-u%C5%BCytkowe/6743-zabudowana-dzia%C5%82ka-nr-478-o-pow-0%2C0703-ha%2C-po%C5%82o%C5%BCona-przy-placu-piastowskim-i-przetarg",
          "wadium_deadline": null,
          "viewing_date": null
        }
      ]
    },
    {
      "key": "koscielnej|6|3",
      "street": "Kościelna",
      "street_norm": "koscielnej",
      "building": "6",
      "apt": "3",
      "kind": "unknown",
      "listings": [
        {
          "date": "2026-05-29",
          "round": null,
          "kind": "unknown",
          "outcome": "announced",
          "wykaz_no": null
        }
      ]
    },
    {
      "key": "koscielnej|4-5|4",
      "street": "Kościelna",
      "street_norm": "koscielnej",
      "building": "4-5",
      "apt": "4",
      "kind": "unknown",
      "listings": [
        {
          "date": "2026-05-29",
          "round": null,
          "kind": "unknown",
          "outcome": "announced",
          "wykaz_no": null
        }
      ]
    },
    {
      "key": "adama mickiewicza|3|2",
      "street": "Adama Mickiewicza",
      "street_norm": "adama mickiewicza",
      "building": "3",
      "apt": "2",
      "kind": "unknown",
      "listings": [
        {
          "date": "2026-05-29",
          "round": null,
          "kind": "unknown",
          "outcome": "announced",
          "wykaz_no": null
        }
      ]
    },
    {
      "key": "komuny paryskiej|8|1",
      "street": "Komuny Paryskiej",
      "street_norm": "komuny paryskiej",
      "building": "8",
      "apt": "1",
      "kind": "unknown",
      "listings": [
        {
          "date": "2026-04-07",
          "round": null,
          "kind": "unknown",
          "outcome": "announced",
          "wykaz_no": "77/2026"
        }
      ]
    },
    {
      "key": "rynek|29-30|9",
      "street": "Rynek",
      "street_norm": "rynek",
      "building": "29-30",
      "apt": "9",
      "kind": "unknown",
      "listings": [
        {
          "date": "2026-03-06",
          "round": null,
          "kind": "unknown",
          "outcome": "announced",
          "wykaz_no": null
        }
      ]
    },
    {
      "key": "marcina opitza|20|3",
      "street": "Marcina Opitza",
      "street_norm": "marcina opitza",
      "building": "20",
      "apt": "3",
      "kind": "unknown",
      "listings": [
        {
          "date": "2026-02-03",
          "round": null,
          "kind": "unknown",
          "outcome": "announced",
          "wykaz_no": "35/2026"
        }
      ]
    },
    {
      "key": "wesolej|8|3",
      "street": "Wesołej",
      "street_norm": "wesolej",
      "building": "8",
      "apt": "3",
      "kind": "unknown",
      "listings": [
        {
          "date": "2025-11-25",
          "round": null,
          "kind": "unknown",
          "outcome": "announced",
          "wykaz_no": null
        }
      ]
    }
  ]
}
