{
  "Osiedle Wschód|21/65": null,
  "Centrum|61/3": null,
  "Centrum|62/4": null,
  "Sadlno|19/6": null,
  "Centrum|129/5": null,
  "Centrum|129/6": null,
  "Stolec|399/6": null,
  "Osiedle Wschód|8/2": null,
  "Brodziszów|442/1": null,
  "Brodziszów|442/2": null,
  "Osiedle Wschód|3/6": null,
  "Osiedle Wschód|13/2": null,
  "Strąkowa|203": null,
  "Sadlno|20/2": null,
  "Pawłowice|132/5": null,
  "Pawłowice|132/4": null,
  "Centrum|16/11": null,
  "Pawłowice|132/6": null,
  "Centrum|82/4": null,
  "Pawłowice|132/9": null,
  "Pawłowice|132/8": null,
  "Pawłowice|132/7": null,
  "Centrum|37/1": null,
  "Osiedle Wschód|21/48": null,
  "Centrum|34/2": null,
  "Sadlno|20/14": null,
  "Sadlno|20/13": null,
  "Sadlno|20/12": null,
  "Sadlno|20/11": null,
  "Sadlno|20/10": null,
  "Sadlno|20/9": null,
  "Sadlno|20/8": null,
  "Sadlno|20/7": null,
  "Sadlno|20/6": null,
  "Sadlno|20/5": null,
  "Sadlno|20/4": null,
  "Sadlno|20/3": null,
  "Pawłowice|17/5": null,
  "Pawłowice|17/4": null,
  "Pawłowice|17/1": null,
  "Pawłowice|17/3": null,
  "Pawłowice|17/2": null,
  "Centrum|37/25": null,
  "Centrum|14": null,
  "Sadlno|104/4": null,
  "Osiedle Wschód|21/61": null,
  "Osiedle Wschód|21/59": null,
  "Centrum|27/3": null
}
